MovieTool/__init__.py
MovieTool/download_torrents.py
MovieTool/ombi_handler.py
MovieTool/torrent_handler.py
MovieTool-3.8.3.dist-info/LICENSE
MovieTool-3.8.3.dist-info/METADATA
MovieTool-3.8.3.dist-info/WHEEL
MovieTool-3.8.3.dist-info/top_level.txt
MovieTool-3.8.3.dist-info/RECORD
