Metadata-Version: 2.1
Name: MovieTool
Version: 3.8.3
Summary: =?utf-8?q?Descarga_tus_peliculas_y_series=2C_automatiza_todo_y_crea_tu_propio_Netflix_=28hecho_con_fines_de_aprendizaje=29_completamente_funcional_=28y_con_m=C3=A1s_contenido_que_el_de_Netflix=29_haciendo_uso_de_Plex=2C_Ombi_y_otras_tecnolog=C3=ADas_m=C3=A1s=2E_=E2=AD=90?=
Home-page: https://github.com/ElHaban3ro/MovieTool
Author: ElHaban3ro
Author-email: habanferd@gmail.com
License: MIT
Keywords: python,torrent,torrent-management,movies,plex,hbo,series,netflix,ombi,peliculas
Classifier: Programming Language :: Python :: 3.10
License-File: LICENSE
Requires-Dist: pandas (==1.4.4)
Requires-Dist: python-qbittorrent (==0.4.2)
Requires-Dist: feedparser (==6.0.10)
